projectend.py
projectend-0.14.0.dist-info/entry_points.txt
projectend-0.14.0.dist-info/LICENSE
projectend-0.14.0.dist-info/WHEEL
projectend-0.14.0.dist-info/METADATA
projectend-0.14.0.dist-info/RECORD
