Metadata-Version: 2.1
Name: projectend
Version: 0.14.0
Summary: calculate the end of projects
Home-page: https://github.com/ganwell/projectend
License: AGPL-3.0-or-later
Author: Jean-Louis Fuchs
Author-email: jean-louis.fuchs@adfinis-sygroup.ch
Requires-Python: >=3.9,<4.0
Classifier: Intended Audience :: Developers
Classifier: License :: OSI Approved :: GNU Affero General Public License v3 or later (AGPLv3+)
Classifier: Operating System :: OS Independent
Classifier: Programming Language :: Python :: 3
Classifier: Programming Language :: Python :: 3.7
Classifier: Programming Language :: Python :: 3.9
Requires-Dist: click (>=7.1.2)
Requires-Dist: intervaltree (>=3.1.0)
Requires-Dist: toml (>=0.10.2)
Project-URL: Repository, https://github.com/ganwell/projectend
